{"form":{"control":"Form","elements":[{"control":"Text","props":{"value":"Static Styled Value","control":"Text","css":"color: blue;\nfont-weight: bold;"},"uid":"1562680234155"},{"control":"Input","props":{"value":{"source":"value"},"control":"Input","label":"Modify this and bound text below will change","css":"margin-top: 20px;"},"uid":"1562680234157"},{"control":"Text","props":{"value":{"source":"value"},"control":"Text"},"uid":"1562680234158"}],"uid":"P-0"},"schema":{"type":"object","properties":{"value":{"type":"string","title":"value","uid":"1562680234156"}},"uid":"1562680234154"},"style":{},"uid":"text","modified":1562680533167}